upstox_auto_login/__init__.py
upstox_auto_login/login.py
upstox_auto_login-0.1.5.dist-info/METADATA
upstox_auto_login-0.1.5.dist-info/WHEEL
upstox_auto_login-0.1.5.dist-info/top_level.txt
upstox_auto_login-0.1.5.dist-info/RECORD
