Metadata-Version: 2.4
Name: upstox-auto-login
Version: 0.1.5
Summary: Automated Upstox login using Selenium and TOTP
Author-email: Uttam <uttamraj5050@gmail.com>
License: MIT
Project-URL: Homepage, https://github.com/uttam04/upstox-auto-login
Requires-Python: >=3.8
Requires-Dist: selenium>=4.0
Requires-Dist: pyotp
Requires-Dist: requests
